devispoken2written/__init__.py
spoken2written/__init__.py
devispoken2written-0.0.1.dist-info/METADATA
devispoken2written-0.0.1.dist-info/WHEEL
devispoken2written-0.0.1.dist-info/top_level.txt
devispoken2written-0.0.1.dist-info/RECORD
